sciviso/__init__.py
sciviso/__main__.py
sciviso/api.py
sciviso/barchart.py
sciviso/boxplot.py
sciviso/charts.py
sciviso/countplot.py
sciviso/emapplot.py
sciviso/heatmap.py
sciviso/histogram.py
sciviso/line.py
sciviso/sankey.py
sciviso/scatterplot.py
sciviso/stats.py
sciviso/violinplot.py
sciviso/vis.py
sciviso/volcanoplot.py
sciviso-1.1.1.data/data/LICENSE
sciviso-1.1.1.dist-info/LICENSE
sciviso-1.1.1.dist-info/METADATA
sciviso-1.1.1.dist-info/WHEEL
sciviso-1.1.1.dist-info/entry_points.txt
sciviso-1.1.1.dist-info/top_level.txt
sciviso-1.1.1.dist-info/RECORD
