Metadata-Version: 2.1
Name: sciviso
Version: 1.1.1
Summary: sciviso: Wrapper for common visualisations for sci constellation.
Home-page: https://github.com/ArianeMora/sciviso
Author: Ariane Mora
Author-email: ariane.n.mora@gmail.com
License: GPL3
Project-URL: Bug Tracker, https://github.com/ArianeMora/sciviso/issues
Project-URL: Documentation, https://github.com/ArianeMora/sciviso
Project-URL: Source Code, https://github.com/ArianeMora/sciviso
Keywords: util
Classifier: Intended Audience :: Science/Research
Classifier: License :: OSI Approved :: GNU General Public License v3 (GPLv3)
Classifier: Natural Language :: English
Classifier: Operating System :: OS Independent
Classifier: Programming Language :: Python :: 3.6
Classifier: Programming Language :: Python :: 3.7
Classifier: Programming Language :: Python :: 3.8
Classifier: Topic :: Scientific/Engineering :: Bio-Informatics
Requires-Python: >=3.6
License-File: LICENSE
Requires-Dist: sciutil
Requires-Dist: pandas
Requires-Dist: numpy
Requires-Dist: matplotlib
Requires-Dist: statannot
Requires-Dist: seaborn
Requires-Dist: adjustText
Requires-Dist: wordcloud
Requires-Dist: networkx
Requires-Dist: dash
Requires-Dist: kaleido
